{
  "udemy": [
    "/udemyGorsel?kategori=python",
    "/udemy?kategori=python",
    "/udemy/python"
  ],
  "hava":[
    "/havaGorsel?il=canakkale&ilce=merkez",
    "/hava?il=hatay&ilce=samandag",
    "/hava/mardin/nusaybin"
  ],
  "eczane": [
    "/eczaneGorsel?il=canakkale&ilce=merkez",
    "/eczane?il=hatay&ilce=samandag",
    "/eczane/mardin/nusaybin"
  ],
  "ezan": [
    "/ezanGorsel?il=canakkale",
    "/ezan?il=hatay",
    "/ezan/mardin"
  ],
  "google": [
    "/googleGorsel?ara=lorem impsum sit amet",
    "/google?ara=lorem impsum sit amet",
    "/google/lorem impsum sit amet"
  ],
  "youtube": [
    "",
    "/youtube?link=https://www.youtube.com/watch?v=1YlwjEQzMdU",
    ""
  ],
  "trendyol": [
    "",
    "/trendyol?link=https://www.trendyol.com/soly/meltblown-filtre-3-katli-tam-ultrasonik-cerrahi-maske-yesil-100-adet-p-47636885",
    ""
  ],
  "deprem":[
    "/depremGorsel",
    "/deprem",
    ""
  ],
  "akaryakit":[
    "/akaryakitGorsel",
    "/akaryakit",
    ""
  ],
  "haber": [
    "/haberGorsel",
    "/haber",
    ""
  ],
  "bim": [
    "/bimGorsel",
    "/bim",
    ""
  ],
  "doviz": [
    "/dovizGorsel",
    "/doviz",
    ""
  ]
}